README.md
setup.cfg
setup.py
TOPSIS_Dhruv_101803466.egg-info/PKG-INFO
TOPSIS_Dhruv_101803466.egg-info/SOURCES.txt
TOPSIS_Dhruv_101803466.egg-info/dependency_links.txt
TOPSIS_Dhruv_101803466.egg-info/entry_points.txt
TOPSIS_Dhruv_101803466.egg-info/requires.txt
TOPSIS_Dhruv_101803466.egg-info/top_level.txt
src/topsis.py