Metadata-Version: 2.1
Name: TOPSIS-Dhruv-101803466
Version: 3.0.2
Summary: TOPSIS implementation.
Home-page: https://pypi.org/project/TOPSIS-Dhruv-101803466/
Author: Dhruv Bansal
Author-email: dbansal_be18@thapar.edu
License: MIT
Platform: UNKNOWN
Classifier: License :: OSI Approved :: MIT License
Classifier: Programming Language :: Python :: 3
Classifier: Programming Language :: Python :: 3.4
Classifier: Programming Language :: Python :: 3.5
Classifier: Programming Language :: Python :: 3.6
Classifier: Programming Language :: Python :: 3.7
